downloader/__init__.py
downloader/py.typed
downloader/cli/__init__.py
downloader/cli/entry_point.py
downloader/main/__init__.py
downloader/main/downloader.py
downloader/main/main.py
downloader/main/progress.py
fire_downloader-1.0.3.dist-info/LICENSE
fire_downloader-1.0.3.dist-info/METADATA
fire_downloader-1.0.3.dist-info/WHEEL
fire_downloader-1.0.3.dist-info/entry_points.txt
fire_downloader-1.0.3.dist-info/top_level.txt
fire_downloader-1.0.3.dist-info/RECORD
