Metadata-Version: 2.1
Name: fire-downloader
Version: 1.0.3
Summary: Package for downloading urls
Author-email: Quinten Roets <qdr2104@columbia.edu>
License: MIT
Project-URL: Source Code, https://github.com/quintenroets/downloader
Requires-Python: >=3.10
License-File: LICENSE
Requires-Dist: package-utils <1,>=0.6.1
Requires-Dist: python-dateutil <3,>=2.8.2
Requires-Dist: requests <3,>=2.31.0
Requires-Dist: retry <1,>=0.9.2
Requires-Dist: superpathlib <3,>=2.0.1
Requires-Dist: tqdm <5,>=4.66.1
Provides-Extra: dev
Requires-Dist: package-dev-tools <1,>=0.5.11 ; extra == 'dev'
Requires-Dist: package-dev-utils <1,>=0.1.6 ; extra == 'dev'
Requires-Dist: types-python-dateutil <3,>=2.9.0.20240316 ; extra == 'dev'
Requires-Dist: types-requests <3,>=2.32.0.20240622 ; extra == 'dev'
Requires-Dist: types-retry <1,>=0.9.9.4 ; extra == 'dev'
Requires-Dist: types-tqdm <5,>=4.66.0.20240417 ; extra == 'dev'
